autoFillMaskWithCandy/__init__.py
autoFillMaskWithCandy/autoFillMaskWithCandy.py
autoFillMaskWithCandy-0.0.4.dist-info/LICENSE.txt
autoFillMaskWithCandy-0.0.4.dist-info/METADATA
autoFillMaskWithCandy-0.0.4.dist-info/WHEEL
autoFillMaskWithCandy-0.0.4.dist-info/top_level.txt
autoFillMaskWithCandy-0.0.4.dist-info/RECORD
