Metadata-Version: 2.1
Name: autoFillMaskWithCandy
Version: 0.0.4
Summary: Automatically mask sentences from a given input where certain words vary, and fil-mask from given candidates
Home-page: https://github.com/Elashico/autoFillMaskWithCandy.git
Author: Elatot
Author-email: <elashiishii@gmail.com>
License: MIT
Keywords: python,hugging-face,fill-mask,natural language processing,pretrained langugae model
Classifier: Development Status :: 1 - Planning
Classifier: Intended Audience :: Developers
Classifier: Programming Language :: Python :: 3
Classifier: Operating System :: Unix
Classifier: Operating System :: MacOS :: MacOS X
Classifier: Operating System :: Microsoft :: Windows
License-File: LICENSE.txt
Requires-Dist: torch
Requires-Dist: transformers
